morphy_hive_1_ti_client/__init__.py
morphy_hive_1_ti_client/api_client.py
morphy_hive_1_ti_client/api_response.py
morphy_hive_1_ti_client/configuration.py
morphy_hive_1_ti_client/exceptions.py
morphy_hive_1_ti_client/py.typed
morphy_hive_1_ti_client/rest.py
morphy_hive_1_ti_client/api/__init__.py
morphy_hive_1_ti_client/api/default_api.py
morphy_hive_1_ti_client/models/__init__.py
morphy_hive_1_ti_client/models/compress_text200_response.py
morphy_hive_1_ti_client/models/compress_text_request.py
morphy_hive_1_ti_client/models/expand_text200_response.py
morphy_hive_1_ti_client/models/expand_text_request.py
morphy_hive_1_ti_client-1.0.0.dist-info/METADATA
morphy_hive_1_ti_client-1.0.0.dist-info/WHEEL
morphy_hive_1_ti_client-1.0.0.dist-info/top_level.txt
morphy_hive_1_ti_client-1.0.0.dist-info/RECORD
